pandaPlus/__init__.py
pandaPlus/pandasPlus.py
pandaPlus-0.3.dist-info/pandasPlus.egg-info/dependency_links.txt
pandaPlus-0.3.dist-info/pandasPlus.egg-info/top_level.txt
pandasPlus/__init__.py
pandasPlus/pandasPlus.py
pandaPlus-0.3.dist-info/LICENSE
pandaPlus-0.3.dist-info/METADATA
pandaPlus-0.3.dist-info/WHEEL
pandaPlus-0.3.dist-info/top_level.txt
pandaPlus-0.3.dist-info/RECORD
