Metadata-Version: 2.1
Name: pandaPlus
Version: 0.3
Home-page: https://github.com/tiaramathur/
Author: Tiara Mathur
Author-email: mathurtiara@gmail.com
License: MIT
Keywords: pandas,formatting,dataframes
License-File: LICENSE
Requires-Dist: pandas
Requires-Dist: xlsxwriter
